gravatarcontacts/__init__.py
gravatarcontacts/__main__.py
gravatarcontacts/google_contacts.py
gravatarcontacts/gravatar.py
gravatarcontacts_cmenon12-1.0.5.dist-info/LICENSE
gravatarcontacts_cmenon12-1.0.5.dist-info/METADATA
gravatarcontacts_cmenon12-1.0.5.dist-info/WHEEL
gravatarcontacts_cmenon12-1.0.5.dist-info/top_level.txt
gravatarcontacts_cmenon12-1.0.5.dist-info/RECORD
