Metadata-Version: 2.1
Name: gravatarcontacts-cmenon12
Version: 1.0.5
Summary: A package to copy Gravatar profile pictures to your Google Contacts.
Home-page: https://github.com/cmenon12/gravatar-to-google-contacts
Author: Christopher Menon
License: GNU GPLv3
Platform: UNKNOWN
Classifier: Programming Language :: Python :: 3
Classifier: License :: OSI Approved :: GNU Affero General Public License v3 or later (AGPLv3+)
Classifier: Operating System :: OS Independent
Classifier: Natural Language :: English
Requires-Python: >=3.7
Requires-Dist: requests (>=2.23.0)
Requires-Dist: google-api-python-client (>=1.8.3)
Requires-Dist: google-auth-oauthlib (>=0.4.1)
Requires-Dist: libgravatar (>=0.2.3)
Requires-Dist: Pillow (>=7.1.2)
Requires-Dist: protobuf (>=3.11.0)
